sphinx_feature_flags/__init__.py
sphinx_feature_flags/sphinx_feature_flags.py
sphinx_feature_flags-1.0.9.dist-info/LICENSE
sphinx_feature_flags-1.0.9.dist-info/METADATA
sphinx_feature_flags-1.0.9.dist-info/WHEEL
sphinx_feature_flags-1.0.9.dist-info/RECORD
