Metadata-Version: 2.1
Name: sphinx_feature_flags
Version: 1.0.9
Summary: This Sphinx extension allows for the `feature-flag` directive to hide/show content based on build-time flags.
License: MIT
Author: Xsolla Backend
Author-email: xbe@xsolla.com
Requires-Python: >=3.10
Classifier: Framework :: Sphinx :: Extension
Classifier: Intended Audience :: Developers
Classifier: License :: OSI Approved :: MIT License
Classifier: Operating System :: OS Independent
Classifier: Programming Language :: Python :: 3
Classifier: Programming Language :: Python :: 3.10
Classifier: Programming Language :: Python :: 3.11
Classifier: Programming Language :: Python :: 3.12
Classifier: Programming Language :: Python :: 3.13
Classifier: Topic :: Software Development :: Build Tools
Classifier: Topic :: Software Development :: Documentation
Requires-Dist: sphinx (>=7.3.7)
Project-URL: Homepage, https://github.com/Unidocs1/sphinx_feature_flags
Project-URL: Issues, https://github.com/Unidocs1/sphinx_feature_flags/issues
